LICENSE
README.md
setup.py
hecalib/__init__.py
hecalib/chou.py
hecalib/daniilidis.py
hecalib/hand_eye_calibration.py
hecalib/li.py
hecalib/lu.py
hecalib/park.py
hecalib/tsai.py
hecalib.egg-info/PKG-INFO
hecalib.egg-info/SOURCES.txt
hecalib.egg-info/dependency_links.txt
hecalib.egg-info/not-zip-safe
hecalib.egg-info/top_level.txt