Metadata-Version: 2.1
Name: hecalib
Version: 1.3.0
Summary: A python library for different implementations of handeye calibration for vision guided robots
Home-page: https://github.com/ienebuse/hecalib
Author: Ikenna Enebuse
Author-email: i.enebuse@gmail.com
Classifier: Programming Language :: Python :: 3
Classifier: License :: OSI Approved :: MIT License
Classifier: Operating System :: OS Independent
License-File: LICENSE
